{"file:///d%3A/mgr/xdb/src/lib.rs":{"language":"Rust","code":4,"comment":0,"blank":1},"file:///d%3A/mgr/xdb/Cargo.toml":{"language":"TOML","code":17,"comment":0,"blank":4},"file:///d%3A/mgr/xdb/src/searcher.rs":{"language":"Rust","code":173,"comment":10,"blank":27},"file:///d%3A/mgr/xdb/src/ip_value.rs":{"language":"Rust","code":53,"comment":0,"blank":10},"file:///d%3A/mgr/xdb/benches/search.rs":{"language":"Rust","code":46,"comment":0,"blank":6},"file:///d%3A/mgr/sea-orm-adapter/CHANGELOG.md":{"language":"Markdown","code":25,"comment":0,"blank":17},"file:///d%3A/mgr/sea-orm-adapter/README.md":{"language":"Markdown","code":24,"comment":0,"blank":10},"file:///d%3A/mgr/sea-orm-adapter/src/lib.rs":{"language":"Rust","code":7,"comment":0,"blank":3},"file:///d%3A/mgr/sea-orm-adapter/examples/rbac_with_domains_policy.csv":{"language":"CSV","code":6,"comment":0,"blank":1},"file:///d%3A/mgr/sea-orm-adapter/src/migration.rs":{"language":"Rust","code":59,"comment":2,"blank":6},"file:///d%3A/mgr/server/static/rbac_model.conf":{"language":"Properties","code":10,"comment":0,"blank":5},"file:///d%3A/mgr/sea-orm-adapter/src/entity.rs":{"language":"Rust","code":17,"comment":1,"blank":5},"file:///d%3A/mgr/sea-orm-adapter/examples/rbac_with_domains_model.conf":{"language":"Properties","code":10,"comment":0,"blank":4},"file:///d%3A/mgr/sea-orm-adapter/src/action.rs":{"language":"Rust","code":220,"comment":0,"blank":24},"file:///d%3A/mgr/server/static/casbin/rbac_with_domains_policy.csv":{"language":"CSV","code":6,"comment":0,"blank":1},"file:///d%3A/mgr/server/static/casbin/rbac_with_domains_model.conf":{"language":"Properties","code":10,"comment":0,"blank":4},"file:///d%3A/mgr/sea-orm-adapter/src/adapter.rs":{"language":"Rust","code":427,"comment":14,"blank":67},"file:///d%3A/mgr/sea-orm-adapter/.rustfmt.toml":{"language":"TOML","code":11,"comment":2,"blank":1},"file:///d%3A/mgr/server/service/Cargo.toml":{"language":"TOML","code":19,"comment":0,"blank":3},"file:///d%3A/mgr/sea-orm-adapter/Cargo.toml":{"language":"TOML","code":40,"comment":6,"blank":7},"file:///d%3A/mgr/server/shared/Cargo.toml":{"language":"TOML","code":45,"comment":0,"blank":2},"file:///d%3A/mgr/server/shared/README.md":{"language":"Markdown","code":9,"comment":0,"blank":3},"file:///d%3A/mgr/server/settings/production.toml":{"language":"TOML","code":29,"comment":0,"blank":4},"file:///d%3A/mgr/server/settings/development.toml":{"language":"TOML","code":29,"comment":1,"blank":4},"file:///d%3A/mgr/server/router/src/lib.rs":{"language":"Rust","code":1,"comment":0,"blank":0},"file:///d%3A/mgr/server/shared/src/lib.rs":{"language":"Rust","code":5,"comment":0,"blank":0},"file:///d%3A/mgr/server/service/src/lib.rs":{"language":"Rust","code":2,"comment":0,"blank":0},"file:///d%3A/mgr/server/router/Cargo.toml":{"language":"TOML","code":10,"comment":0,"blank":3},"file:///d%3A/mgr/server/model/Cargo.toml":{"language":"TOML","code":13,"comment":0,"blank":3},"file:///d%3A/mgr/server/shared/src/constant.rs":{"language":"Rust","code":55,"comment":29,"blank":9},"file:///d%3A/mgr/server/router/src/admin/sys_role_route.rs":{"language":"Rust","code":41,"comment":0,"blank":8},"file:///d%3A/mgr/server/model/README.md":{"language":"Markdown","code":14,"comment":0,"blank":3},"file:///d%3A/mgr/server/router/src/admin/mod.rs":{"language":"Rust","code":11,"comment":0,"blank":1},"file:///d%3A/mgr/server/router/src/admin/sys_access_key_route.rs":{"language":"Rust","code":32,"comment":0,"blank":8},"file:///d%3A/mgr/server/service/src/helper/redis_helper.rs":{"language":"Rust","code":84,"comment":5,"blank":3},"file:///d%3A/mgr/server/router/src/admin/sys_organization_route.rs":{"language":"Rust","code":21,"comment":0,"blank":8},"file:///d%3A/mgr/server/router/src/admin/sys_sandbox_route.rs":{"language":"Rust","code":16,"comment":0,"blank":5},"file:///d%3A/mgr/server/router/src/admin/sys_operation_log_route.rs":{"language":"Rust","code":22,"comment":0,"blank":6},"file:///d%3A/mgr/server/router/src/admin/sys_menu_route.rs":{"language":"Rust","code":62,"comment":0,"blank":9},"file:///d%3A/mgr/server/router/src/admin/sys_login_log_route.rs":{"language":"Rust","code":21,"comment":0,"blank":7},"file:///d%3A/mgr/server/model/src/admin/mod.rs":{"language":"Rust","code":2,"comment":0,"blank":0},"file:///d%3A/mgr/server/router/src/admin/sys_endpoint_route.rs":{"language":"Rust","code":36,"comment":0,"blank":7},"file:///d%3A/mgr/server/router/src/admin/sys_domain_route.rs":{"language":"Rust","code":41,"comment":0,"blank":8},"file:///d%3A/mgr/server/model/src/lib.rs":{"language":"Rust","code":2,"comment":0,"blank":1},"file:///d%3A/mgr/server/model/src/admin/response/mod.rs":{"language":"Rust","code":5,"comment":0,"blank":1},"file:///d%3A/mgr/server/router/src/admin/sys_authentication_route.rs":{"language":"Rust","code":42,"comment":4,"blank":9},"file:///d%3A/mgr/server/router/src/admin/sys_user_route.rs":{"language":"Rust","code":53,"comment":0,"blank":5},"file:///d%3A/mgr/server/model/src/admin/request/mod.rs":{"language":"Rust","code":11,"comment":0,"blank":1},"file:///d%3A/mgr/server/service/src/helper/mod.rs":{"language":"Rust","code":2,"comment":0,"blank":1},"file:///d%3A/mgr/server/service/src/helper/db_helper.rs":{"language":"Rust","code":18,"comment":1,"blank":3},"file:///d%3A/mgr/server/model/src/admin/response/sys_authentication.rs":{"language":"Rust","code":20,"comment":2,"blank":5},"file:///d%3A/mgr/server/model/src/admin/response/sys_domain.rs":{"language":"Rust","code":8,"comment":0,"blank":2},"file:///d%3A/mgr/server/model/src/admin/response/sys_endpoint.rs":{"language":"Rust","code":12,"comment":0,"blank":2},"file:///d%3A/mgr/server/model/src/admin/request/sys_access_key.rs":{"language":"Rust","code":18,"comment":0,"blank":5},"file:///d%3A/mgr/server/model/src/admin/response/sys_menu.rs":{"language":"Rust","code":79,"comment":0,"blank":7},"file:///d%3A/mgr/server/model/src/admin/request/sys_authentication.rs":{"language":"Rust","code":9,"comment":0,"blank":2},"file:///d%3A/mgr/server/shared/src/global.rs":{"language":"Rust","code":186,"comment":36,"blank":29},"file:///d%3A/mgr/server/model/src/admin/response/sys_user.rs":{"language":"Rust","code":49,"comment":0,"blank":5},"file:///d%3A/mgr/server/model/src/entities/product_category.rs":{"language":"Rust","code":21,"comment":1,"blank":5},"file:///d%3A/mgr/server/shared/src/utils/memory_nonce_store.rs":{"language":"Rust","code":34,"comment":17,"blank":7},"file:///d%3A/mgr/server/shared/src/web/validator.rs":{"language":"Rust","code":106,"comment":7,"blank":9},"file:///d%3A/mgr/server/model/src/entities/product_comment.rs":{"language":"Rust","code":26,"comment":1,"blank":5},"file:///d%3A/mgr/server/service/src/admin/sys_access_key_service.rs":{"language":"Rust","code":168,"comment":4,"blank":32},"file:///d%3A/mgr/server/service/src/admin/mod.rs":{"language":"Rust","code":15,"comment":0,"blank":1},"file:///d%3A/mgr/server/service/src/admin/sys_authorization_service.rs":{"language":"Rust","code":292,"comment":4,"blank":61},"file:///d%3A/mgr/server/service/src/admin/sys_login_log_service.rs":{"language":"Rust","code":51,"comment":0,"blank":9},"file:///d%3A/mgr/server/model/src/entities/product_brand.rs":{"language":"Rust","code":18,"comment":1,"blank":5},"file:///d%3A/mgr/server/model/src/entities/receive_address.rs":{"language":"Rust","code":22,"comment":1,"blank":5},"file:///d%3A/mgr/server/shared/src/utils/ip.rs":{"language":"Rust","code":95,"comment":51,"blank":14},"file:///d%3A/mgr/server/service/src/admin/sys_endpoint_service.rs":{"language":"Rust","code":168,"comment":5,"blank":27},"file:///d%3A/mgr/server/model/src/entities/sys_user_role.rs":{"language":"Rust","code":40,"comment":1,"blank":7},"file:///d%3A/mgr/server/service/src/admin/event_handler/auth_event_handler.rs":{"language":"Rust","code":48,"comment":2,"blank":9},"file:///d%3A/mgr/server/model/src/entities/sys_tokens.rs":{"language":"Rust","code":26,"comment":1,"blank":5},"file:///d%3A/mgr/server/service/src/admin/event_handler/mod.rs":{"language":"Rust","code":1,"comment":0,"blank":0},"file:///d%3A/mgr/server/model/src/entities/sys_user.rs":{"language":"Rust","code":50,"comment":1,"blank":7},"file:///d%3A/mgr/server/model/src/entities/sys_role_menu.rs":{"language":"Rust","code":42,"comment":1,"blank":7},"file:///d%3A/mgr/server/model/src/entities/sys_menu.rs":{"language":"Rust","code":44,"comment":1,"blank":6},"file:///d%3A/mgr/server/model/src/entities/sys_role.rs":{"language":"Rust","code":45,"comment":1,"blank":8},"file:///d%3A/mgr/server/model/src/entities/sys_login_log.rs":{"language":"Rust","code":23,"comment":1,"blank":5},"file:///d%3A/mgr/server/model/src/entities/sys_operation_log.rs":{"language":"Rust","code":31,"comment":1,"blank":5},"file:///d%3A/mgr/server/shared/src/utils/tree_util.rs":{"language":"Rust","code":190,"comment":65,"blank":26},"file:///d%3A/mgr/server/service/src/admin/sys_user_service.rs":{"language":"Rust","code":135,"comment":0,"blank":24},"file:///d%3A/mgr/server/service/src/admin/sys_role_service.rs":{"language":"Rust","code":124,"comment":0,"blank":25},"file:///d%3A/mgr/server/model/src/entities/sys_endpoint.rs":{"language":"Rust","code":19,"comment":1,"blank":5},"file:///d%3A/mgr/server/shared/src/utils/secure_util.rs":{"language":"Rust","code":50,"comment":0,"blank":13},"file:///d%3A/mgr/server/service/src/admin/sys_organization_service.rs":{"language":"Rust","code":48,"comment":0,"blank":9},"file:///d%3A/mgr/server/model/src/entities/sys_domain.rs":{"language":"Rust","code":21,"comment":1,"blank":5},"file:///d%3A/mgr/server/service/src/admin/sys_operation_log_service.rs":{"language":"Rust","code":103,"comment":0,"blank":16},"file:///d%3A/mgr/server/shared/src/utils/nonce_store.rs":{"language":"Rust","code":35,"comment":16,"blank":9},"file:///d%3A/mgr/server/shared/src/utils/redis_nonce_store.rs":{"language":"Rust","code":75,"comment":7,"blank":12},"file:///d%3A/mgr/server/model/src/entities/sea_orm_active_enums.rs":{"language":"Rust","code":20,"comment":1,"blank":2},"file:///d%3A/mgr/server/model/src/entities/sys_access_key.rs":{"language":"Rust","code":21,"comment":1,"blank":5},"file:///d%3A/mgr/server/shared/src/utils/mod.rs":{"language":"Rust","code":81,"comment":6,"blank":12},"file:///d%3A/mgr/server/model/src/entities/product_spu.rs":{"language":"Rust","code":33,"comment":1,"blank":5},"file:///d%3A/mgr/server/service/src/admin/sys_menu_service.rs":{"language":"Rust","code":257,"comment":0,"blank":41},"file:///d%3A/mgr/server/service/src/admin/sys_domain_service.rs":{"language":"Rust","code":133,"comment":0,"blank":29},"file:///d%3A/mgr/server/model/src/entities/product_sku.rs":{"language":"Rust","code":22,"comment":1,"blank":5},"file:///d%3A/mgr/server/model/src/entities/product_attribute_value.rs":{"language":"Rust","code":17,"comment":1,"blank":5},"file:///d%3A/mgr/server/model/src/entities/product_attribute_category.rs":{"language":"Rust","code":15,"comment":1,"blank":5},"file:///d%3A/mgr/server/service/src/admin/sys_auth_service.rs":{"language":"Rust","code":345,"comment":20,"blank":39},"file:///d%3A/mgr/server/shared/src/utils/hash.rs":{"language":"Rust","code":38,"comment":0,"blank":7},"file:///d%3A/mgr/server/service/src/admin/errors/sys_role_error.rs":{"language":"Rust","code":28,"comment":0,"blank":5},"file:///d%3A/mgr/server/shared/src/web/request_id.rs":{"language":"Rust","code":53,"comment":0,"blank":12},"file:///d%3A/mgr/server/service/src/admin/event/access_token_event.rs":{"language":"Rust","code":45,"comment":0,"blank":6},"file:///d%3A/mgr/server/shared/src/web/res.rs":{"language":"Rust","code":66,"comment":0,"blank":11},"file:///d%3A/mgr/server/service/src/admin/errors/sys_menu_error.rs":{"language":"Rust","code":28,"comment":0,"blank":5},"file:///d%3A/mgr/server/service/src/admin/event/login_log_event.rs":{"language":"Rust","code":39,"comment":0,"blank":5},"file:///d%3A/mgr/server/service/src/admin/event/mod.rs":{"language":"Rust","code":2,"comment":0,"blank":1},"file:///d%3A/mgr/server/service/src/admin/errors/sys_access_key_error.rs":{"language":"Rust","code":25,"comment":0,"blank":4},"file:///d%3A/mgr/server/service/src/admin/errors/mod.rs":{"language":"Rust","code":5,"comment":0,"blank":1},"file:///d%3A/mgr/server/service/src/admin/errors/sys_domain_error.rs":{"language":"Rust","code":34,"comment":0,"blank":4},"file:///d%3A/mgr/server/shared/src/web/page.rs":{"language":"Rust","code":42,"comment":0,"blank":7},"file:///d%3A/mgr/server/model/src/entities/sys_organization.rs":{"language":"Rust","code":22,"comment":1,"blank":5},"file:///d%3A/mgr/server/service/src/admin/errors/sys_user_error.rs":{"language":"Rust","code":37,"comment":0,"blank":4},"file:///d%3A/mgr/server/shared/src/utils/dir.rs":{"language":"Rust","code":29,"comment":0,"blank":6},"file:///d%3A/mgr/server/model/src/admin/request/sys_user.rs":{"language":"Rust","code":38,"comment":0,"blank":7},"file:///d%3A/mgr/server/model/src/entities/product_attribute.rs":{"language":"Rust","code":20,"comment":1,"blank":5},"file:///d%3A/mgr/server/model/src/entities/prelude.rs":{"language":"Rust","code":25,"comment":1,"blank":2},"file:///d%3A/mgr/server/shared/src/utils/api_key_middleware.rs":{"language":"Rust","code":194,"comment":34,"blank":34},"file:///d%3A/mgr/server/model/src/admin/request/sys_role.rs":{"language":"Rust","code":36,"comment":0,"blank":9},"file:///d%3A/mgr/server/shared/src/web/operation_log.rs":{"language":"Rust","code":366,"comment":53,"blank":66},"file:///d%3A/mgr/server/shared/src/web/mod.rs":{"language":"Rust","code":7,"comment":0,"blank":0},"file:///d%3A/mgr/server/model/src/admin/request/sys_organization.rs":{"language":"Rust","code":8,"comment":0,"blank":3},"file:///d%3A/mgr/server/shared/src/utils/api_key.rs":{"language":"Rust","code":187,"comment":93,"blank":30},"file:///d%3A/mgr/server/model/src/entities/order_item.rs":{"language":"Rust","code":25,"comment":1,"blank":5},"file:///d%3A/mgr/server/shared/src/web/error.rs":{"language":"Rust","code":81,"comment":0,"blank":15},"file:///d%3A/mgr/server/model/src/entities/mod.rs":{"language":"Rust","code":27,"comment":1,"blank":3},"file:///d%3A/mgr/server/model/src/entities/order.rs":{"language":"Rust","code":38,"comment":1,"blank":5},"file:///d%3A/mgr/server/model/src/entities/cart_item.rs":{"language":"Rust","code":24,"comment":1,"blank":5},"file:///d%3A/mgr/server/model/src/entities/casbin_rule.rs":{"language":"Rust","code":18,"comment":1,"blank":5},"file:///d%3A/mgr/server/model/src/admin/request/sys_operation_log.rs":{"language":"Rust","code":8,"comment":0,"blank":2},"file:///d%3A/mgr/server/shared/src/web/auth.rs":{"language":"Rust","code":111,"comment":0,"blank":19},"file:///d%3A/mgr/server/model/src/admin/request/sys_menu.rs":{"language":"Rust","code":64,"comment":0,"blank":7},"file:///d%3A/mgr/server/model/src/admin/request/sys_endpoint.rs":{"language":"Rust","code":8,"comment":0,"blank":3},"file:///d%3A/mgr/server/model/src/admin/request/sys_login_log.rs":{"language":"Rust","code":8,"comment":0,"blank":1},"file:///d%3A/mgr/server/model/src/admin/request/sys_domain.rs":{"language":"Rust","code":33,"comment":0,"blank":5},"file:///d%3A/mgr/server/model/src/admin/request/sys_authorization.rs":{"language":"Rust","code":30,"comment":0,"blank":9},"file:///d%3A/mgr/server/middleware/Cargo.toml":{"language":"TOML","code":16,"comment":0,"blank":2},"file:///d%3A/mgr/server/api/Cargo.toml":{"language":"TOML","code":15,"comment":0,"blank":3},"file:///d%3A/mgr/server/config/README.md":{"language":"Markdown","code":2,"comment":0,"blank":0},"file:///d%3A/mgr/server/service/src/admin/dto/sys_auth_dto.rs":{"language":"Rust","code":12,"comment":0,"blank":2},"file:///d%3A/mgr/server/config/Cargo.toml":{"language":"TOML","code":30,"comment":0,"blank":2},"file:///d%3A/mgr/server/bin/Cargo.toml":{"language":"TOML","code":30,"comment":1,"blank":4},"file:///d%3A/mgr/server/api/src/lib.rs":{"language":"Rust","code":1,"comment":0,"blank":0},"file:///d%3A/mgr/README.md":{"language":"Markdown","code":61,"comment":4,"blank":29},"file:///d%3A/mgr/server/initialize/Cargo.toml":{"language":"TOML","code":37,"comment":0,"blank":2},"file:///d%3A/mgr/rustfmt.toml":{"language":"TOML","code":27,"comment":21,"blank":3},"file:///d%3A/mgr/server/config/src/config.rs":{"language":"Rust","code":11,"comment":6,"blank":7},"file:///d%3A/mgr/server/bin/src/product.rs":{"language":"Rust","code":3,"comment":0,"blank":1},"file:///d%3A/mgr/server/service/src/admin/dto/mod.rs":{"language":"Rust","code":1,"comment":0,"blank":1},"file:///d%3A/mgr/server/initialize/src/event_channel_initialization.rs":{"language":"Rust","code":21,"comment":0,"blank":2},"file:///d%3A/mgr/server/initialize/src/access_key_initialization.rs":{"language":"Rust","code":7,"comment":0,"blank":5},"file:///d%3A/mgr/server/bin/src/user.rs":{"language":"Rust","code":3,"comment":0,"blank":1},"file:///d%3A/mgr/server/initialize/src/config_initialization.rs":{"language":"Rust","code":9,"comment":0,"blank":2},"file:///d%3A/mgr/server/config/src/profile.rs":{"language":"Rust","code":24,"comment":0,"blank":2},"file:///d%3A/mgr/server/config/src/redis.rs":{"language":"Rust","code":36,"comment":20,"blank":7},"file:///d%3A/mgr/server/bin/src/pay.rs":{"language":"Rust","code":3,"comment":0,"blank":1},"file:///d%3A/mgr/server/bin/src/order.rs":{"language":"Rust","code":3,"comment":0,"blank":1},"file:///d%3A/mgr/server/config/src/lib.rs":{"language":"Rust","code":73,"comment":8,"blank":11},"file:///d%3A/mgr/server/config/src/kafka.rs":{"language":"Rust","code":10,"comment":0,"blank":1},"file:///d%3A/mgr/server/initialize/src/casbin_initialization.rs":{"language":"Rust","code":18,"comment":0,"blank":5},"file:///d%3A/mgr/server/initialize/src/db_initialization.rs":{"language":"Rust","code":86,"comment":6,"blank":7},"file:///d%3A/mgr/server/initialize/src/lib.rs":{"language":"Rust","code":22,"comment":0,"blank":2},"file:///d%3A/mgr/server/initialize/src/jwt_initialization.rs":{"language":"Rust","code":28,"comment":0,"blank":8},"file:///d%3A/mgr/server/config/src/server.rs":{"language":"Rust","code":6,"comment":0,"blank":2},"file:///d%3A/mgr/server/initialize/src/ip2region_initialization.rs":{"language":"Rust","code":10,"comment":0,"blank":2},"file:///d%3A/mgr/server/initialize/src/log_tracing_init.rs":{"language":"Rust","code":30,"comment":0,"blank":7},"file:///d%3A/mgr/server/api/src/admin/sys_authentication_api.rs":{"language":"Rust","code":89,"comment":6,"blank":15},"file:///d%3A/mgr/server/initialize/src/server_initialization.rs":{"language":"Rust","code":10,"comment":0,"blank":5},"file:///d%3A/mgr/server/api/src/admin/mod.rs":{"language":"Rust","code":11,"comment":0,"blank":0},"file:///d%3A/mgr/server/api/src/admin/sys_access_key_api.rs":{"language":"Rust","code":26,"comment":0,"blank":5},"file:///d%3A/mgr/server/initialize/src/redis_initialization.rs":{"language":"Rust","code":131,"comment":2,"blank":26},"file:///d%3A/mgr/server/bin/src/auth.rs":{"language":"Rust","code":3,"comment":0,"blank":1},"file:///d%3A/mgr/server/config/src/jwt.rs":{"language":"Rust","code":7,"comment":3,"blank":2},"file:///d%3A/mgr/server/api/src/admin/sys_login_log_api.rs":{"language":"Rust","code":17,"comment":0,"blank":4},"file:///d%3A/mgr/server/api/src/admin/sys_endpoint_api.rs":{"language":"Rust","code":45,"comment":0,"blank":9},"file:///d%3A/mgr/server/api/src/admin/sys_menu_api.rs":{"language":"Rust","code":61,"comment":0,"blank":10},"file:///d%3A/mgr/server/api/src/admin/sys_domain_api.rs":{"language":"Rust","code":38,"comment":0,"blank":7},"file:///d%3A/mgr/server/config/src/database.rs":{"language":"Rust","code":14,"comment":0,"blank":3},"file:///d%3A/mgr/server/bin/src/admin.rs":{"language":"Rust","code":36,"comment":13,"blank":6},"file:///d%3A/mgr/server/api/src/admin/sys_organization_api.rs":{"language":"Rust","code":17,"comment":0,"blank":3},"file:///d%3A/mgr/server/api/src/admin/sys_operation_log_api.rs":{"language":"Rust","code":17,"comment":0,"blank":3},"file:///d%3A/mgr/server/initialize/src/admin_router_initialization.rs":{"language":"Rust","code":305,"comment":38,"blank":34},"file:///d%3A/mgr/server/bin/src/cart.rs":{"language":"Rust","code":0,"comment":0,"blank":1},"file:///d%3A/mgr/server/middleware/src/lib.rs":{"language":"Rust","code":2,"comment":0,"blank":1},"file:///d%3A/mgr/server/api/src/admin/sys_sandbox_api.rs":{"language":"Rust","code":10,"comment":0,"blank":4},"file:///d%3A/mgr/server/api/src/admin/sys_user_api.rs":{"language":"Rust","code":75,"comment":0,"blank":12},"file:///d%3A/mgr/server/middleware/src/jwt_middleware.rs":{"language":"Rust","code":46,"comment":2,"blank":4},"file:///d%3A/mgr/server/api/src/admin/sys_role_api.rs":{"language":"Rust","code":41,"comment":0,"blank":9},"file:///d%3A/mgr/Cargo.toml":{"language":"TOML","code":121,"comment":104,"blank":4},"file:///d%3A/mgr/server/middleware/src/jwt_util.rs":{"language":"Rust","code":69,"comment":6,"blank":15},"file:///d%3A/mgr/docker-compose.yml":{"language":"YAML","code":111,"comment":116,"blank":3},"file:///d%3A/mgr/codegen/README.md":{"language":"Markdown","code":7,"comment":0,"blank":0},"file:///d%3A/mgr/codegen/src/lib.rs":{"language":"Rust","code":174,"comment":6,"blank":26},"file:///d%3A/mgr/codegen/Cargo.toml":{"language":"TOML","code":10,"comment":0,"blank":3},"file:///d%3A/mgr/migration/Cargo.lock":{"language":"TOML","code":2959,"comment":2,"blank":332},"file:///d%3A/mgr/codegen/server/model/src/admin/input/sys_role.rs":{"language":"Rust","code":36,"comment":0,"blank":5},"file:///d%3A/mgr/codegen/server/service/src/admin/sys_role_service.rs":{"language":"Rust","code":130,"comment":0,"blank":26},"file:///d%3A/mgr/codegen/server/api/src/admin/sys_role_api.rs":{"language":"Rust","code":45,"comment":0,"blank":7},"file:///d%3A/mgr/codegen/Cargo.lock":{"language":"TOML","code":353,"comment":2,"blank":50},"file:///d%3A/mgr/codegen/server/service/src/admin/errors/sys_role_error.rs":{"language":"Rust","code":28,"comment":0,"blank":5},"file:///d%3A/mgr/axum-casbin/tests/test_set_enforcer.rs":{"language":"Rust","code":59,"comment":31,"blank":20},"file:///d%3A/mgr/axum-casbin/examples/rbac_with_domains_model.conf":{"language":"Properties","code":10,"comment":0,"blank":4},"file:///d%3A/mgr/axum-casbin/examples/rbac_with_domains_policy.csv":{"language":"CSV","code":6,"comment":0,"blank":1},"file:///d%3A/mgr/migration/README.md":{"language":"Markdown","code":40,"comment":0,"blank":20},"file:///d%3A/mgr/axum-casbin/tests/test_middleware_domain.rs":{"language":"Rust","code":57,"comment":21,"blank":17},"file:///d%3A/mgr/axum-casbin/Cargo.toml":{"language":"TOML","code":33,"comment":1,"blank":8},"file:///d%3A/mgr/axum-casbin/tests/test_middleware.rs":{"language":"Rust","code":57,"comment":30,"blank":20},"file:///d%3A/mgr/migration/Cargo.toml":{"language":"TOML","code":20,"comment":4,"blank":3},"file:///d%3A/mgr/axum-casbin/src/lib.rs":{"language":"Rust","code":3,"comment":0,"blank":2},"file:///d%3A/mgr/.env":{"language":"Properties","code":2,"comment":0,"blank":1},"file:///d%3A/mgr/.dockerignore":{"language":"Ignore","code":3,"comment":0,"blank":0},"file:///d%3A/mgr/Cargo.lock":{"language":"TOML","code":5993,"comment":2,"blank":617},"file:///d%3A/mgr/axum-casbin/src/middleware.rs":{"language":"Rust","code":231,"comment":13,"blank":24},"file:///d%3A/mgr/migration/src/main.rs":{"language":"Rust","code":6,"comment":1,"blank":2},"file:///d%3A/mgr/migration/src/data/mod.rs":{"language":"Rust","code":7,"comment":0,"blank":0},"file:///d%3A/mgr/migration/src/schemas/m20240815_000002_create_sys_user.rs":{"language":"Rust","code":84,"comment":3,"blank":9},"file:///d%3A/mgr/migration/src/lib.rs":{"language":"Rust","code":63,"comment":4,"blank":2},"file:///d%3A/mgr/migration/src/schemas/m20241023_000003_create_sys_role.rs":{"language":"Rust","code":66,"comment":0,"blank":8},"file:///d%3A/mgr/migration/src/schemas/m20240815_000001_create_enum_status.rs":{"language":"Rust","code":70,"comment":4,"blank":11},"file:///d%3A/mgr/migration/src/data/m20241024_000007_insert_casbin_rule.rs":{"language":"Rust","code":66,"comment":3,"blank":17},"file:///d%3A/mgr/migration/src/data/m20241024_000006_insert_sys_role_menu.rs":{"language":"Rust","code":35,"comment":0,"blank":7},"file:///d%3A/mgr/.idea/modules.xml":{"language":"XML","code":8,"comment":0,"blank":0},"file:///d%3A/mgr/migration/src/schemas/m20241023_000004_create_sys_access_key.rs":{"language":"Rust","code":67,"comment":0,"blank":8},"file:///d%3A/mgr/.idea/vcs.xml":{"language":"XML","code":7,"comment":0,"blank":0},"file:///d%3A/mgr/migration/src/schemas/m20241023_000006_create_sys_domain.rs":{"language":"Rust","code":64,"comment":0,"blank":8},"file:///d%3A/mgr/migration/src/data/m20241024_000005_insert_sys_user_role.rs":{"language":"Rust","code":25,"comment":0,"blank":7},"file:///d%3A/mgr/migration/src/data/m20241024_000003_insert_sys_role.rs":{"language":"Rust","code":24,"comment":0,"blank":7},"file:///d%3A/mgr/.idea/mgr.iml":{"language":"XML","code":27,"comment":0,"blank":0},"file:///d%3A/mgr/migration/src/data/m20241024_000002_insert_sys_user.rs":{"language":"Rust","code":24,"comment":0,"blank":7},"file:///d%3A/mgr/migration/src/schemas/m20241023_000007_create_sys_endpoint.rs":{"language":"Rust","code":53,"comment":0,"blank":5},"file:///d%3A/mgr/migration/src/data/m20241024_000004_insert_sys_menu.rs":{"language":"Rust","code":36,"comment":0,"blank":7},"file:///d%3A/mgr/migration/src/schemas/m20241023_000008_create_sys_login_log.rs":{"language":"Rust","code":65,"comment":0,"blank":5},"file:///d%3A/mgr/migration/src/schemas/m20241023_000009_create_sys_menu.rs":{"language":"Rust","code":97,"comment":0,"blank":8},"file:///d%3A/mgr/migration/src/schemas/m20241023_000018_create_cart_item.rs":{"language":"Rust","code":93,"comment":3,"blank":3},"file:///d%3A/mgr/migration/src/schemas/m20241023_000016_create_order.rs":{"language":"Rust","code":201,"comment":7,"blank":3},"file:///d%3A/mgr/migration/src/data/m20241023_000001_insert_sys_domain.rs":{"language":"Rust","code":21,"comment":8,"blank":10},"file:///d%3A/mgr/migration/src/schemas/m20241023_000015_create_event_streams.rs":{"language":"Rust","code":0,"comment":207,"blank":27},"file:///d%3A/mgr/migration/src/schemas/m20241023_000017_create_receive_address.rs":{"language":"Rust","code":100,"comment":3,"blank":5},"file:///d%3A/mgr/migration/src/schemas/m20241023_000014_create_sys_user_role.rs":{"language":"Rust","code":41,"comment":2,"blank":7},"file:///d%3A/mgr/migration/src/schemas/m20241023_000013_create_sys_tokens.rs":{"language":"Rust","code":67,"comment":0,"blank":5},"file:///d%3A/mgr/migration/src/schemas/mod.rs":{"language":"Rust","code":18,"comment":0,"blank":1},"file:///d%3A/mgr/migration/src/schemas/m20241023_000019_create_product.rs":{"language":"Rust","code":481,"comment":24,"blank":13},"file:///d%3A/mgr/migration/src/schemas/m20241023_000010_create_sys_operation_log.rs":{"language":"Rust","code":103,"comment":0,"blank":5},"file:///d%3A/mgr/migration/src/schemas/m20241023_000012_create_sys_role_menu.rs":{"language":"Rust","code":58,"comment":3,"blank":8},"file:///d%3A/mgr/migration/src/schemas/m20241023_000011_create_sys_organization.rs":{"language":"Rust","code":74,"comment":0,"blank":8}}